trufflehog_installer/__init__.py
trufflehog_installer/trufflehog.py
trufflehog.1-1.0.dist-info/METADATA
trufflehog.1-1.0.dist-info/WHEEL
trufflehog.1-1.0.dist-info/entry_points.txt
trufflehog.1-1.0.dist-info/top_level.txt
trufflehog.1-1.0.dist-info/RECORD
