Metadata-Version: 2.1
Name: trufflehog.1
Version: 1.0
Summary: TruffleHog - Find secrets in your code
License: MIT
Classifier: Programming Language :: Python :: 3
Classifier: License :: OSI Approved :: MIT License
Classifier: Operating System :: OS Independent
Requires-Python: >=3.6
